lydialib/__init__.py
lydialib/lydiamod.py
lydialib-0.1.0.dist-info/METADATA
lydialib-0.1.0.dist-info/WHEEL
lydialib-0.1.0.dist-info/top_level.txt
lydialib-0.1.0.dist-info/RECORD
