Metadata-Version: 2.1
Name: lydialib
Version: 0.1.0
Summary: lydialib
Home-page: https://t.me/lydialib
Author: https://t.me/cagavo
Author-email: no@no.com
License: nothing
Platform: UNKNOWN
Classifier: Development Status :: 1 - Planning
Classifier: Intended Audience :: Religion
Classifier: License :: Freeware
Classifier: Natural Language :: Italian
Classifier: Operating System :: OS Independent
Classifier: Programming Language :: Python
